blazebase/__init__.py
blazebase/blazebase.py
blazebase/exceptions.py
blazebase-0.1.0.dist-info/METADATA
blazebase-0.1.0.dist-info/WHEEL
blazebase-0.1.0.dist-info/RECORD
